precountify/__init__.py
precountify/_version.py
precountify/cli.py
precountify/click.py
precountify/margin.py
precountify/music.py
precountify/precount.py
precountify/precountify.py
precountify/util.py
precountify/audio/__init__.py
precountify/audio/audio_file.py
precountify/audio/mono.py
precountify/audio/stereo.py
precountify/data/click.wav
precountify/estimator/__init__.py
precountify/estimator/essentia.py
precountify/estimator/librosa.py
precountify/estimator/madmom.py
precountify/estimator/tempo_estimator.py
precountify-1.0.0.dist-info/LICENSE
precountify-1.0.0.dist-info/METADATA
precountify-1.0.0.dist-info/WHEEL
precountify-1.0.0.dist-info/entry_points.txt
precountify-1.0.0.dist-info/top_level.txt
precountify-1.0.0.dist-info/RECORD
