Metadata-Version: 2.1
Name: precountify
Version: 1.0.0
Summary: A tool for pre-countifying
Home-page: https://github.com/akiomik/precountify
Author: Akiomi Kamakura
Author-email: akiomik@gmail.com
License: Apache License 2.0
Keywords: audio-processing
Platform: any
Classifier: Environment :: Console
Classifier: License :: OSI Approved :: Apache Software License
Classifier: Operating System :: OS Independent
Classifier: Programming Language :: Python
Classifier: Programming Language :: Python :: 3
Classifier: Programming Language :: Python :: 3 :: Only
Classifier: Programming Language :: Python :: 3.4
Classifier: Programming Language :: Python :: 3.5
Classifier: Programming Language :: Python :: 3.6
Classifier: Programming Language :: Python :: 3.7
Classifier: Topic :: Multimedia :: Sound/Audio
Classifier: Topic :: Multimedia :: Sound/Audio :: Sound Synthesis
Classifier: Topic :: Utilities
Requires-Python: >=3.4
Requires-Dist: fire
Requires-Dist: librosa
Provides-Extra: essentia
Requires-Dist: essentia (==2.1b5) ; extra == 'essentia'
Provides-Extra: madmom
Requires-Dist: madmom ; extra == 'madmom'
